Metadata-Version: 1.2
Name: torauth
Version: 0.0.1
Summary: An authentication, registration, account management for Tornado.
Home-page: https://github.com/longniao/torauth
Author: Longniao
Author-email: longniao@gmail.com
Maintainer: Longniao
Maintainer-email: longniao@gmail.com
License: MIT
Keywords: tornado torstack auth account social openid twitter facebook oauth wechat weixin
Platform: any
Classifier: Development Status :: 5 - Production/Stable
Classifier: Environment :: Console
Classifier: Intended Audience :: Developers
Classifier: License :: OSI Approved :: MIT License
Classifier: Operating System :: OS Independent
Classifier: Programming Language :: Python
Classifier: Programming Language :: Python :: 3.5
Classifier: Programming Language :: Python :: 3.6
Classifier: Programming Language :: Python :: 3.7
Requires-Python: >=3.5
